Metadata-Version: 2.1
Name: changer
Version: 3.0
Summary: Changer is - Arabic English Persian Hindi Chinese Malayalam Thai Bengali - Python library to convert numbers from-to.
Home-page: https://github.com/azwri/changer
Author: Azwri
Author-email: aazwri@gmail.com
License: MIT
Keywords: Change Convert Arabic English Persian Hindi Chinese Malayalam Thai Bengali from to
Platform: UNKNOWN
Classifier: Development Status :: 5 - Production/Stable
Classifier: Operating System :: OS Independent
Classifier: License :: OSI Approved :: MIT License
Classifier: Programming Language :: Python :: 3
